gusto_app_integration/__init__.py
gusto_app_integration/_hooks/__init__.py
gusto_app_integration/_hooks/registration.py
gusto_app_integration/_hooks/sdkhooks.py
gusto_app_integration/_hooks/types.py
gusto_app_integration/_version.py
gusto_app_integration/basesdk.py
gusto_app_integration/companies.py
gusto_app_integration/companybenefits.py
gusto_app_integration/companylocations.py
gusto_app_integration/contractorpaymentgroups.py
gusto_app_integration/contractorpayments.py
gusto_app_integration/contractors.py
gusto_app_integration/departments.py
gusto_app_integration/earningtypes.py
gusto_app_integration/employeeaddresses.py
gusto_app_integration/employeebenefits.py
gusto_app_integration/employeeemployments.py
gusto_app_integration/employees.py
gusto_app_integration/events.py
gusto_app_integration/garnishments.py
gusto_app_integration/httpclient.py
gusto_app_integration/introspection.py
gusto_app_integration/jobs.py
gusto_app_integration/jobsandcompensations.py
gusto_app_integration/locations.py
gusto_app_integration/models/__init__.py
gusto_app_integration/models/accruing_time_off_hour.py
gusto_app_integration/models/accruing_time_off_hour_object.py
gusto_app_integration/models/admin.py
gusto_app_integration/models/apierror.py
gusto_app_integration/models/authentication.py
gusto_app_integration/models/benefit_summary.py
gusto_app_integration/models/benefit_type_requirements.py
gusto_app_integration/models/child_support_data.py
gusto_app_integration/models/company.py
gusto_app_integration/models/company_address.py
gusto_app_integration/models/company_benefit.py
gusto_app_integration/models/company_benefit_with_employee_benefits.py
gusto_app_integration/models/company_custom_field.py
gusto_app_integration/models/company_custom_field_list.py
gusto_app_integration/models/compensation.py
gusto_app_integration/models/contractor.py
gusto_app_integration/models/contractor_payment.py
gusto_app_integration/models/contractor_payment_for_group.py
gusto_app_integration-0.2.4.dist-info/METADATA
gusto_app_integration-0.2.4.dist-info/WHEEL
gusto_app_integration-0.2.4.dist-info/RECORD
